README.md
pyproject.toml
setup.py
src/physbo_core_cython/__init__.py
src/physbo_core_cython.egg-info/PKG-INFO
src/physbo_core_cython.egg-info/SOURCES.txt
src/physbo_core_cython.egg-info/dependency_links.txt
src/physbo_core_cython.egg-info/requires.txt
src/physbo_core_cython.egg-info/top_level.txt
src/physbo_core_cython/gp/__init__.py
src/physbo_core_cython/gp/cov/__init__.py
src/physbo_core_cython/gp/cov/_src/__init__.py
src/physbo_core_cython/gp/cov/_src/enhance_gauss.c
src/physbo_core_cython/gp/cov/_src/enhance_gauss.pyx
src/physbo_core_cython/misc/__init__.py
src/physbo_core_cython/misc/_src/__init__.py
src/physbo_core_cython/misc/_src/cythonized.c
src/physbo_core_cython/misc/_src/cythonized.pyx