Metadata-Version: 2.4
Name: physbo-core-cython
Version: 3.0.0
Summary: cythonized core modules for physbo
Author-email: PHYSBO developers <physbo-dev@issp.u-tokyo.ac.jp>
License-Expression: MPL-2.0
Project-URL: homepage, https://www.pasums.issp.u-tokyo.ac.jp/physbo/en
Project-URL: source, https://github.com/issp-center-dev/physbo-core-cython
Requires-Python: >=3.9
Requires-Dist: numpy
Provides-Extra: cython
Requires-Dist: Cython; extra == "cython"
